{
  "users": [
    {
      "name": "נעם לביא",
      "mahlaka": "מרתף הקסמים",
      "grades": {
        "test1": "70",
        "test2": "80",
        "test3": "90",
        "test4": "100"
      }
    },
    {
      "name": "שקד בוקעי",
      "mahlaka": "מרתף הקסמים",
      "grades": {
        "test1": "68",
        "test2": "84",
        "test3": "96",
        "test4": "100"
      }
    },
    {
      "name": "כעעיעי",
      "mahlaka": "מרתף הקסמים",
      "grades": {
        "test1": "86",
        "test2": "78",
        "test3": "90",
        "test4": "50"
      }
    }
  ],
  "tirgulim": {
    "value": [
      {
        "timeline": 1,
        "items": [
          {
            "id": 1,
            "numOfQue": "10",
            "Subject": "שיעור חפיפה 1- הכרת הגדוד",
            "Title": "aboutThePloga",
            "Img": "printer.jpg"
          },
          {
            "id": 2,
            "numOfQue": "10",
            "Subject": "שיעור חפיפה 2- חומרה ומחשבים",
            "Title": "CMD",
            "Img": "CMD.png"
          },
          {
            "id": 3,
            "numOfQue": "10",
            "Subject": "שיעור חפיפה 3- ממשקים במחשב",
            "Title": "pcOperation",
            "Img": "pc.jpg"
          }
        ]
      },
      {
        "timeline": 2,
        "items": [
          {
            "id": 4,
            "Subject": "שיעור חפיפה 4- דומיין ותפעול מחשב",
            "Title": "hardware&bios",
            "Img": "bios.png"
          },
          {
            "id": 5,
            "Subject": "שיעור חפיפה 5- תקשורת",
            "Title": "discs",
            "Img": "disc.png"
          }
        ]
      },
      {
        "timeline": 3,
        "items": [
          {
            "id": 6,
            "Subject": "שיעור חפיפה 6- דיסקים ותוכנות",
            "Title": "aboutThePloga",
            "Img": "active-directory-logo2.png"
          },
          {
            "id": 7,
            "Subject": "שיעור חפיפה 7- התקנים חיצוניים",
            "Title": "mail&identifyManage",
            "Img": "mail.jpg"
          },
          {
            "id": 8,
            "Subject": "שיעור חפיפה 8- התקנת מחשב וצהלנט",
            "Title": "control&SCCM",
            "Img": "SCCM.png"
          }
        ]
      },
      {
        "timeline": 4,
        "items": [
          {
            "id": 9,
            "Subject": "שיעור חפיפה 9- פקל משוב, XRM, SCCM, תקלות נפוצות",
            "Title": "aboutThePloga",
            "Img": "active-directory-logo2.png"
          },
          {
            "id": 10,
            "Subject": "שיעור חפיפה 10- הגדרות משתמשים",
            "Title": "userSettings",
            "Img": "mail.jpg"
          }
        ]
      },
      {
        "timeline": 5,
        "items": [
          {
            "id": 11,
            "Subject": "שיעור חפיפה 13- מערכות מבצעיות (טהא, MOIP, ZTUBE, משואה)",
            "Title": "server&commands",
            "Img": "fileServer.jpg"
          },
          {
            "id": 12,
            "Subject": "שיעור חפיפה 14- מצפה, מערכות מיוחדות",
            "Title": "specialSystems",
            "Img": "printer.jpg"
          },
          {
            "id": 13,
            "Subject": "שיעור חפיפה 15 - מערכות מבצעיות (עין סערה, ענן מידע, SEAGULL)",
            "Title": "systems1",
            "Img": "printer.jpg"
          },
          {
            "id": 14,
            "Subject": "שיעור חפיפה 16- מערכות מבצעיות (כפר לוקאלי, כפג, BE, שדה תעופה )",
            "Title": "systems2",
            "Img": "printer.jpg"
          }
        ]
      }
    ]
  },

  "practices": {
    "value": [
      {
        "Title": "תרגול שיעור 2",
        "id": 1,
        "lessonId": 2,
        "routeName": "line"
      },

      {
        "Title": "תרגול שיעור 3 חלק א",
        "id": 1,
        "lessonId": 3,
        "routeName": "bbb"
      },
      {
        "Title": "תרגול שיעור 3 חלק ב",
        "id": 2,
        "lessonId": 3,
        "routeName": "ccc"
      },
      {
        "Title": "תרגול שיעור 4 חלק א",
        "id": 1,
        "lessonId": 4,
        "routeName": "ddd"
      },
      {
        "Title": "תרגול שיעור 4 חלק ב",
        "id": 2,
        "lessonId": 4,
        "routeName": "eee"
      },
      {
        "Title": "תרגול שיעור 5 חלק א",
        "id": 1,
        "lessonId": 5,
        "routeName": "fff"
      },
      {
        "Title": "תרגול שיעור 5 חלק ב",
        "id": 2,
        "lessonId": 5,
        "routeName": "ggg"
      }
    ]
  },

  "exam2": {
    "value": [
      {
        "instructions": [
          "*מבחן זה רשום בלשון זכר אך פונה אל כל המגדרים כלשון אחד.",
          "*בכל שאלה בה אופן הטיפול כולל סיוע של צוות נוסף, יש לציין את דרך הפנייה אל הצוות ואת הפרטים הנחוצים."
        ],
        "exam": [
          {
            "part": "חלק א' – בסיס (27 נקודות)",
            "type": "subQue",
            "questions": [
              {
                "type": "open",
                "que": "הסבר מהו  IMAGEומדוע משתמשים בו. הסבר מהו IMAGE ייעודי וציין אילו מערכות דורשות אותו (4 נק')",
                "inputAns": "",
                "id": 0,
                "points": 4,
                "pointsReceived": "",
                "comments": ""
              },
              {
                "type": "open",
                "que": "הצג בקצרה את שלושת הדרכים שדרכם ניתן להתקין IMAGE על מחשב וציין איזה מערכת הפעלה בכל דרך? (2  נק')",
                "inputAns": "",
                "id": 1,
                "points": 2,
                "pointsReceived": "",
                "comments": ""
              }
            ]
          },
          {
            "type": "subQue",
            "questions": [
              {
                "type": "open",
                "que": "פרט, כיצד נפיץ אימג' משואה על מחשב? מה חשוב לוודא לפני הפצת האימג'? (3 נק')",
                "inputAns": "",
                "id": 2,
                "points": 3,
                "pointsReceived": "",
                "comments": ""
              },
              {
                "type": "open",
                "que": "פרט את שלבי התקנת המשואה לאחר התקנת האימג' (2 נק')",
                "inputAns": "",
                "id": 3,
                "points": 2,
                "pointsReceived": "",
                "comments": ""
              },
              {
                "type": "open",
                "que": "פרט, כיצד נפיץ מפות על משואה? אילו מפות נפיץ? (2 נק')",
                "inputAns": "",
                "id": 4,
                "points": 2,
                "pointsReceived": "",
                "comments": ""
              },
              {
                "type": "open",
                "que": "פרט, מה ההבדל בין משואה אחודה ללקוח? ציין שני הבדלים עיקריים. (2 נק')",
                "inputAns": "",
                "id": 5,
                "points": 2,
                "pointsReceived": "",
                "comments": ""
              }
            ]
          },
          {
            "type": "subQue",
            "questions": [
              {
                "type": "open",
                "que": "איזה 2 מערכות קיימות ברשת הMOIP? ומה הקונבנציה של כל מערכת? (2 נק')",
                "inputAns": "",
                "id": 6,
                "points": 2,
                "pointsReceived": "",
                "comments": ""
              },
              {
                "type": "open",
                "que": "פרט כיצד נתקין MOIP ואיזה אימג' המערכת דורשת?(2 נק')",
                "inputAns": "",
                "id": 7,
                "points": 2,
                "pointsReceived": "",
                "comments": ""
              },
              {
                "type": "open",
                "que": "ציין בקצרה מה השלבים לאחר ההפצת אימג'? (2 נק')",
                "inputAns": "",
                "id": 8,
                "points": 2,
                "pointsReceived": "",
                "comments": ""
              },
              {
                "type": "open",
                "que": "מה הדומיין של MOIP? (1 נק')",
                "inputAns": "",
                "id": 9,
                "points": 1,
                "pointsReceived": "",
                "comments": ""
              }
            ]
          },
          {
            "type": "regularQue",
            "questions": [
              {
                "que": "ציין 2 דרכים להתקנת WIN10 , בחר דרך אחת ופרט כיצד תתקין מחשב WIN10. (3 נק')",
                "type": "open"
              }
            ],
            "inputAns": "",
            "id": 10,
            "points": 3,
            "pointsReceived": "",
            "comments": ""
          },
          {
            "type": "regularQue",
            "questions": [
              {
                "que": "ציין את תפקיד המקשים F2,F8,F9,F10,F12 הבאים בהפעלת המחשב (2 נק')",
                "type": "open"
              }
            ],
            "inputAns": "",
            "id": 11,
            "points": 2,
            "pointsReceived": "",
            "comments": ""
          },
          {
            "type": "subQue",
            "titleQue": "לקוח מתלונן כי לא מצליח לפתוח את ה-PST שלו:",
            "questions": [
              {
                "type": "open",
                "que": "הסבר כיצד נבצע תיקון לPST. (2 נק')",
                "inputAns": "",
                "id": 12,
                "points": 2,
                "pointsReceived": "",
                "comments": ""
              },
              {
                "type": "open",
                "que": "פרט כיצד תפעל במקרה התיקון לא עבד. (נק' 1)",
                "inputAns": "",
                "id": 13,
                "points": 1,
                "pointsReceived": "",
                "comments": ""
              }
            ]
          },
          {
            "type": "subQue",
            "titleQue": "כאשר לקוח מתחבר למחשב מופיעה לו הודעת שגיאה, ציין את פתרונן של השגיאות הבאות:",
            "questions": [
              {
                "type": "open",
                "que": "\"התחום שצוין אינו זמין\" (נק' 1)",
                "inputAns": "",
                "id": 14,
                "points": 1,
                "pointsReceived": "",
                "comments": ""
              },
              {
                "type": "open",
                "que": "\"החשבון שצוין אינו זמין\" (נק' 1)",
                "inputAns": "",
                "id": 15,
                "points": 1,
                "pointsReceived": "",
                "comments": ""
              },
              {
                "type": "open",
                "que": "\"הכרטיס החכם חסום\" (נק' 1)",
                "inputAns": "",
                "id": 16,
                "points": 1,
                "pointsReceived": "",
                "comments": ""
              }
            ]
          },
          {
            "type": "regularQue",
            "questions": [
              {
                "que": "מה עושים כאשר בכוונתנו להיכנס עם הכרטיס למחשב אך אין אופציה של \"הכנס כרטיס חכם\" והאופציה היחידה שמופיעה היא \"ADMINISTRATOR\" ? פרטי את כל דרך הפעולה (2 נק')",
                "type": "open"
              }
            ],
            "inputAns": "",
            "id": 17,
            "points": 2,
            "pointsReceived": "",
            "comments": ""
          }
        ],
        "time": 2700
      }
    ]
  },
  "exam3": {
    "value": [
      {
        "Title": "מהו דומייןמהו דומייןמהו דומייןמהו דומייןמהו דומייןמהו דומייןמהו דומייןמהו דומייןמהו דומ ?",
        "options": [
          "dffdff השונים",
          "תחום פיזי המכיל מספר מחשבים dfd באותו מקום שכולם נמצאים באותו הסגמנט.",
          "תחום לוגי המכיל מספר אובייקטים (כגון: מחשבים, משתמשים וקבוצות). ניתן דרכו ליצור ולערוך את dffd ולהכיל הגדרות על אותם אובייקטים."
        ],
        "type": "american"
      },
      {
        "Title": "איזה ממשק של מייקרוסופט אחראי לניהול אובייקטים בדומיין ?",
        "options": ["SCCM", "IDM", "DSAM", "(AD) ADUC "],
        "type": "american"
      },
      {
        "Title": "איך ניכנס ל-AD ?",
        "type": "open"
      },
      {
        "Title": "איך נתקין את ה-ADUC ?",
        "type": "open"
      },
      {
        "Title": "מה לא ניתן לעשות ב-AD ?",
        "type": "open"
      },
      {
        "Title": "במידה ונרצה לתת הרשאות לתיקייה בשרת למשתמש מסוים, לאיזו קבוצה נוסיף אותו ?",
        "type": "open"
      },
      {
        "Title": "? מתי נפנה לתקנ\"ם",
        "type": "open"
      }
    ]
  },
  "currentUser": {
    "Title": "נועם לביא - גדוד 383/לשכה/ע. קצין טכני",
    "Id": 12345,
    "LoginName": "i:0#.w|army\\s9053078"
  },
  "testsNames": {
    "value": [
      {
        "Title": "exam1",
        "subject": "בוחן 1"
      },
      {
        "Title": "exam2",
        "subject": "בוחן 2"
      },
      {
        "Title": "exam3",
        "subject": "בוחן 3"
      },
      {
        "Title": "exam4",
        "subject": "בוחן 4"
      },
      {
        "Title": "finalTest",
        "subject": "המבחן הסופי"
      }
    ]
  },
  "pendingTests": {
    "value": [
      {
        "Title": "sdsdsd",
        "exam": [
          {
            "part": "חלק א' – בסיס (27 נקודות)",
            "type": "subQue",
            "questions": [
              {
                "type": "open",
                "que": "הסבר מהו  IMAGEומדוע משתמשים בו. הסבר מהו IMAGE ייעודי וציין אילו מערכות דורשות אותו (4 נק')",
                "inputAns": "jkhjhjh",
                "id": 0,
                "points": 4,
                "pointsReceived": "",
                "comments": ""
              },
              {
                "type": "open",
                "que": "הצג בקצרה את שלושת הדרכים שדרכם ניתן להתקין IMAGE על מחשב וציין איזה מערכת הפעלה בכל דרך? (2  נק')",
                "inputAns": "hjh",
                "id": 1,
                "points": 2,
                "pointsReceived": "",
                "comments": ""
              }
            ]
          },
          {
            "type": "subQue",
            "questions": [
              {
                "type": "open",
                "que": "פרט, כיצד נפיץ אימג' משואה על מחשב? מה חשוב לוודא לפני הפצת האימג'? (3 נק')",
                "inputAns": "jjj",
                "id": 2,
                "points": 3,
                "pointsReceived": "",
                "comments": ""
              },
              {
                "type": "open",
                "que": "פרט את שלבי התקנת המשואה לאחר התקנת האימג' (2 נק')",
                "inputAns": "hh",
                "id": 3,
                "points": 2,
                "pointsReceived": "",
                "comments": ""
              },
              {
                "type": "open",
                "que": "פרט, כיצד נפיץ מפות על משואה? אילו מפות נפיץ? (2 נק')",
                "inputAns": "h",
                "id": 4,
                "points": 2,
                "pointsReceived": "",
                "comments": ""
              },
              {
                "type": "open",
                "que": "פרט, מה ההבדל בין משואה אחודה ללקוח? ציין שני הבדלים עיקריים. (2 נק')",
                "inputAns": "h",
                "id": 5,
                "points": 2,
                "pointsReceived": "",
                "comments": ""
              }
            ]
          },
          {
            "type": "subQue",
            "questions": [
              {
                "type": "open",
                "que": "איזה 2 מערכות קיימות ברשת הMOIP? ומה הקונבנציה של כל מערכת? (2 נק')",
                "inputAns": "h",
                "id": 6,
                "points": 2,
                "pointsReceived": "",
                "comments": ""
              },
              {
                "type": "open",
                "que": "פרט כיצד נתקין MOIP ואיזה אימג' המערכת דורשת?(2 נק')",
                "inputAns": "h",
                "id": 7,
                "points": 2,
                "pointsReceived": "",
                "comments": ""
              },
              {
                "type": "open",
                "que": "ציין בקצרה מה השלבים לאחר ההפצת אימג'? (2 נק')",
                "inputAns": "h",
                "id": 8,
                "points": 2,
                "pointsReceived": "",
                "comments": ""
              },
              {
                "type": "open",
                "que": "מה הדומיין של MOIP? (1 נק')",
                "inputAns": "h",
                "id": 9,
                "points": 1,
                "pointsReceived": "",
                "comments": ""
              }
            ]
          },
          {
            "type": "regularQue",
            "questions": [
              {
                "que": "ציין 2 דרכים להתקנת WIN10 , בחר דרך אחת ופרט כיצד תתקין מחשב WIN10. (3 נק')",
                "type": "open"
              }
            ],
            "inputAns": "jkhb",
            "id": 10,
            "points": 3,
            "pointsReceived": "",
            "comments": ""
          },
          {
            "type": "regularQue",
            "questions": [
              {
                "que": "ציין את תפקיד המקשים F2,F8,F9,F10,F12 הבאים בהפעלת המחשב (2 נק')",
                "type": "open"
              }
            ],
            "inputAns": "klhj",
            "id": 11,
            "points": 2,
            "pointsReceived": "",
            "comments": ""
          },
          {
            "type": "subQue",
            "titleQue": "לקוח מתלונן כי לא מצליח לפתוח את ה-PST שלו:",
            "questions": [
              {
                "type": "open",
                "que": "הסבר כיצד נבצע תיקון לPST. (2 נק')",
                "inputAns": "klj",
                "id": 12,
                "points": 2,
                "pointsReceived": "",
                "comments": ""
              },
              {
                "type": "open",
                "que": "פרט כיצד תפעל במקרה התיקון לא עבד. (נק' 1)",
                "inputAns": "klj",
                "id": 13,
                "points": 1,
                "pointsReceived": "",
                "comments": ""
              }
            ]
          },
          {
            "type": "subQue",
            "titleQue": "כאשר לקוח מתחבר למחשב מופיעה לו הודעת שגיאה, ציין את פתרונן של השגיאות הבאות:",
            "questions": [
              {
                "type": "open",
                "que": "\"התחום שצוין אינו זמין\" (נק' 1)",
                "inputAns": "kj",
                "id": 14,
                "points": 1,
                "pointsReceived": "",
                "comments": ""
              },
              {
                "type": "open",
                "que": "\"החשבון שצוין אינו זמין\" (נק' 1)",
                "inputAns": "j",
                "id": 15,
                "points": 1,
                "pointsReceived": "",
                "comments": ""
              },
              {
                "type": "open",
                "que": "\"הכרטיס החכם חסום\" (נק' 1)",
                "inputAns": "lkj",
                "id": 16,
                "points": 1,
                "pointsReceived": "",
                "comments": ""
              }
            ]
          },
          {
            "type": "regularQue",
            "questions": [
              {
                "que": "מה עושים כאשר בכוונתנו להיכנס עם הכרטיס למחשב אך אין אופציה של \"הכנס כרטיס חכם\" והאופציה היחידה שמופיעה היא \"ADMINISTRATOR\" ? פרטי את כל דרך הפעולה (2 נק')",
                "type": "open"
              }
            ],
            "inputAns": "lkj",
            "id": 17,
            "points": 2,
            "pointsReceived": "",
            "comments": ""
          }
        ],
        "num": "12345",
        "type": "exam2",
        "name": "בוחן 2"
      }
    ]
  },
  "students": {
    "value": [
      {
        "Title": "נעם",
        "exam2": [
          {
            "type": "subQue",
            "questions": [
              {
                "type": "open",
                "que": "הסבר מהו IMAGE ומדוע משתמשים בו. הסבר מהו IMAGE ייעודי וציין אילו מערכות דורשות אותו (4 נק')",
                "inputAns": "gfg",
                "id": 0,
                "points": 4,
                "pointsReceived": 1,
                "comments": ""
              },
              {
                "type": "open",
                "que": "הצג בקצרה את שלושת הדרכים שדרכם ניתן להתקין IMAGE על מחשב וציין איזה מערכת הפעלה בכל דרך? (2 נק')",
                "inputAns": "jhjh",
                "id": 1,
                "points": 2,
                "pointsReceived": 1,
                "comments": ""
              }
            ]
          },
          {
            "type": "subQue",
            "questions": [
              {
                "type": "open",
                "que": "פרט, כיצד נפיץ אימג' משואה על מחשב? מה חשוב לוודא לפני הפצת האימג'? (3 נק')",
                "inputAns": "hj",
                "id": 2,
                "points": 3,
                "pointsReceived": 1,
                "comments": ""
              },
              {
                "type": "open",
                "que": "פרט את שלבי התקנת המשואה לאחר התקנת האימג' (2 נק')",
                "inputAns": "uih",
                "id": 3,
                "points": 2,
                "pointsReceived": 1,
                "comments": ""
              },
              {
                "type": "open",
                "que": "פרט, כיצד נפיץ מפות על משואה? אילו מפות נפיץ? (2 נק')",
                "inputAns": "uh",
                "id": 4,
                "points": 2,
                "pointsReceived": 1,
                "comments": ""
              },
              {
                "type": "open",
                "que": "פרט, מה ההבדל בין משואה אחודה ללקוח? ציין שני הבדלים עיקריים. (2 נק')",
                "inputAns": "uh",
                "id": 5,
                "points": 2,
                "pointsReceived": 1,
                "comments": ""
              }
            ]
          },
          {
            "type": "subQue",
            "questions": [
              {
                "type": "open",
                "que": "איזה 2 מערכות קיימות ברשת הMOIP? ומה הקונבנציה של כל מערכת? (2 נק')",
                "inputAns": "uih",
                "id": 6,
                "points": 2,
                "pointsReceived": 1,
                "comments": ""
              },
              {
                "type": "open",
                "que": "פרט כיצד נתקין MOIP ואיזה אימג' המערכת דורשת?(2 נק')",
                "inputAns": "uih",
                "id": 7,
                "points": 2,
                "pointsReceived": 1,
                "comments": ""
              },
              {
                "type": "open",
                "que": "ציין בקצרה מה השלבים לאחר ההפצת אימג'? (2 נק')",
                "inputAns": "ui",
                "id": 8,
                "points": 2,
                "pointsReceived": 1,
                "comments": ""
              },
              {
                "type": "open",
                "que": "מה הדומיין של MOIP? (1 נק')",
                "inputAns": "uih",
                "id": 9,
                "points": 1,
                "pointsReceived": 1,
                "comments": ""
              }
            ]
          },
          {
            "type": "regularQue",
            "questions": [
              {
                "que": "ציין 2 דרכים להתקנת WIN10 , בחר דרך אחת ופרט כיצד תתקין מחשב WIN10. (3 נק')",
                "type": "open"
              }
            ],
            "inputAns": "uih",
            "id": 10,
            "points": 3,
            "pointsReceived": 1,
            "comments": ""
          },
          {
            "type": "regularQue",
            "questions": [
              {
                "que": "ציין את תפקיד המקשים F2,F8,F9,F10,F12 הבאים בהפעלת המחשב (2 נק')",
                "type": "open"
              }
            ],
            "inputAns": "iu",
            "id": 11,
            "points": 2,
            "pointsReceived": 1,
            "comments": "fgfgdgf"
          },
          {
            "finalGrade": 12
          }
        ]
      }
    ]
  },
  "isPermissionActive": {
    "value": [
      {
        "Title": "נעם לביא",
        "userNum": "9053078",
        "exam1": false,
        "exam2": false,
        "exam3": false,
        "exam4": false,
        "finalTest": false
      },
      {
        "Title": "לינוי לוי",
        "userNum": "8829036",
        "exam1": false,
        "exam2": false,
        "exam3": false,
        "exam4": false,
        "finalTest": false
      },
      {
        "Title": "שחר ישש",
        "userNum": "9131383",
        "exam1": false,
        "exam2": false,
        "exam3": false,
        "exam4": false,
        "finalTest": false
      },
      {
        "Title": "לרה גרנ",
        "userNum": "9676484",
        "exam1": false,
        "exam2": false,
        "exam3": false,
        "exam4": false,
        "finalTest": false
      },
      {
        "Title": "שחר ישש",
        "userNum": "780840",
        "exam1": false,
        "exam2": false,
        "exam3": false,
        "exam4": false,
        "finalTest": false
      },
      {
        "Title": "שחר ישש",
        "userNum": "870000",
        "exam1": false,
        "exam2": false,
        "exam3": false,
        "exam4": false,
        "finalTest": false
      }
    ]
  },
  "AdminCheck": {
    "value": [
      {
        "admin": "admin"
      }
    ]
  },

  "dffddf": {
    "value": [
      {
        "id": 1,
        "type": "radio",
        "label": "סמן את המשפט הנכון ביותר:",
        "options": [
          "ה-SSD הוא אמצעי אחסון בו המידע נשמר דיגיטלית והוא יקר ומהיר יותר מה-HD.",
          "הm.2- הוא אמצעי האחסון הזול ביותר והמידע בו נשמר באמצעות צריבה על דיסקים.",
          "ה-HD שומר מידע באופן דיגיטלי והוא זול יותר מה-M.2."
        ],
        "value": ""
      },
      {
        "id": 1,
        "type": "lineBetween",
        "label": "מתח קו בין רכיב האחסון לרכיבים המחוברים אליו:",
        "options": [
          "ה-SSD הוא אמצעי אחסון בו המידע נשמר דיגיטלית והוא יקר ומהיר יותר מה-HD.",
          "הm.2- הוא אמצעי האחסון הזול ביותר והמידע בו נשמר באמצעות צריבה על דיסקים.",
          "ה-HD שומר מידע באופן דיגיטלי והוא זול יותר מה-M.2."
        ],
        "answers": ["fgfgf", "abbbb", "nnfff"],
        "value": [
          {
            "opt": "",
            "ans": ""
          },
          {
            "opt": "",
            "ans": ""
          },
          {
            "opt": "",
            "ans": ""
          }
        ]
      },

      {
        "id": 1,
        "type": "complete",
        "label": "השלם את המשפט:",
        "qustion": "ה-HD מחובר..... ללוח האם/ל-BIOS דרך כבל..... SATA/DATA המעביר..... חשמל / מידע.",
        "bankOptions": ["ללוח האם", "ל-BIOS", "SATA", "DATA"]
      },

      {
        "id": 1,
        "type": "bank",
        "label": "מי אני ?",
        "questions": [
          {
            "qustion": "אני לא מתחבר ללוח האם דרך כבל SATA וגם לא דרך כבל לספק כוח:",
            "bankOptions": ["SSD", "HD", "M.2"]
          },
          {
            "qustion": "המידע נשמר בי באופן מגנטי על ידי צריבה על דיסקים:",
            "bankOptions": ["SSD", "HD", "M.2"]
          },
          {
            "qustion": "אני מתחבר ישירות על חריצים ללוח האם:",
            "bankOptions": ["SSD", "HD", "M.2"]
          }
        ]
      },
      {
        "id": 1,
        "type": "radio",
        "label": "מהו תפקידו של ספק הכוח?",
        "options": [
          "להעביר מידע",
          "לשמור את כל המידע שיש לנו במחשב",
          "להמיר את המתח של רשת החשמל הארצית למתח הנדרש ע\"י המחשב",
          "תשובות א' וב' נכונות"
        ],
        "value": ""
      },

      {
        "id": 1,
        "type": "lineBetween",
        "label": "מתח קו בין רכיב החומרה  לתפקידו:",
        "options": ["כרטיס הרחבה", "לוח האם", "כרטיס RAM", "מעבד", "ספק כוח"],
        "answers": [
          "כרטיס שנועד להוסיף חיבורים (פורטים) למחשב או להחליף חיבורים תקולים",
          "יחידת העיבוד המרכזית של המחשב, תפקידו לבצע את כל פעולות המחשב",
          "כרטיס לאחסון זיכרון זמני, עליו נשמרים נתונים שרצים בזמן אמת במחשב. * בלעדיו לא יעלה המחשב.",
          "רכיב אליו מחובר כבל המתח, תפקידו להעביר מתח חשמלי לרכיבי המחשב.",
          "לוח אלקטרוני עליו יושבים כל הרכיבים במחשב, אותם הוא מקשר חשמלית."
        ],
        "value": [
          {
            "opt": "",
            "ans": ""
          },
          {
            "opt": "",
            "ans": ""
          },
          {
            "opt": "",
            "ans": ""
          }
        ]
      },

      {
        "id": 1,
        "type": "radio",
        "label": "מה לא נציין לחברה האזרחית כאשר יש לנו תקלה חומרתית במחשב?",
        "options": [
          "תיאור תקלה",
          "לשמור את כל המידע שיש לנו במחשב",
          "תאריך סיום האחריות",
          "המספר הסידורי שעל המדבקה"
        ],
        "value": ""
      },
      {
        "id": 1,
        "type": "radio",
        "label": "באילו סוגי דגמים של מחשבים אנו משתמשים בצ\"הל",
        "options": [
          "נייחים של HP וניידים של dell בלבד",
          "נייחים של DELL וHP וניידים של LENOVO",
          "נייחים של DELL וניידים של HP וLENOVO",
          "נייחים של HP בלבד וניידים של LENOVO ו DEL"
        ],
        "value": ""
      },
      {
        "id": 1,
        "type": "dragDrop",
        "label": "באילו סוגי דגמים של מחשבים אנו משתמשים בצ\"הל",
        "dropColumns": ["בלמ\"ס", "סודי", "סודי ביותר", "סודי שותף"],
        "dragOptions": [
          "כפ\"ג",
          "כפר לוקאלי",
          "עמדה אפורה",
          "צהלנ\"ט",
          "שדה תעופה",
          "Black Edition",
          "משואה",
          "טירת אגם",
          "עין סערה",
          "סיגל"
        ],
        "value": [
          {
            "opt": "",
            "ans": ""
          },
          {
            "opt": "",
            "ans": ""
          },
          {
            "opt": "",
            "ans": ""
          },
          {
            "opt": "",
            "ans": ""
          },
          {
            "opt": "",
            "ans": ""
          },
          {
            "opt": "",
            "ans": ""
          },
          {
            "opt": "",
            "ans": ""
          },
          {
            "opt": "",
            "ans": ""
          },
          {
            "opt": "",
            "ans": ""
          },
          {
            "opt": "",
            "ans": ""
          }
        ]
      }
    ]
  },

  "practicesData": {
    "value": [
      {
        "id": 1,
        "weekId": 1,
        "lessonName": "line",
        "pracId": 1,
        "data": [
          {
            "id": 1,
            "type": "radio",
            "label": "סמן את המשפט הנכון ביותר:",
            "options": [
              "ה-SSD הוא אמצעי אחסון בו המידע נשמר דיגיטלית והוא יקר ומהיר יותר מה-HD.",
              "הm.2- הוא אמצעי האחסון הזול ביותר והמידע בו נשמר באמצעות צריבה על דיסקים.",
              "ה-HD שומר מידע באופן דיגיטלי והוא זול יותר מה-M.2."
            ],
            "value": ""
          },
          {
            "id": 1,
            "type": "lineBetween",
            "label": "מתח קו בין רכיב האחסון לרכיבים המחוברים אליו:",
            "options": [
              "ה-SSD הוא אמצעי אחסון בו המידע נשמר דיגיטלית והוא יקר ומהיר יותר מה-HD.",
              "הm.2- הוא אמצעי האחסון הזול ביותר והמידע בו נשמר באמצעות צריבה על דיסקים.",
              "ה-HD שומר מידע באופן דיגיטלי והוא זול יותר מה-M.2."
            ],
            "answers": ["fgfgf", "abbbb", "nnfff"],
            "value": [
              { "opt": "", "ans": "" },
              { "opt": "", "ans": "" },
              { "opt": "", "ans": "" }
            ]
          },
          {
            "id": 1,
            "type": "complete",
            "label": "השלם את המשפט:",
            "qustion": "ה-HD מחובר..... ללוח האם/ל-BIOS דרך כבל..... SATA/DATA המעביר..... חשמל / מידע.",
            "bankOptions": ["ללוח האם", "ל-BIOS", "SATA", "DATA"]
          },
          {
            "id": 1,
            "type": "bank",
            "label": "מי אני ?",
            "questions": [
              {
                "qustion": "אני לא מתחבר ללוח האם דרך כבל SATA וגם לא דרך כבל לספק כוח:",
                "bankOptions": ["SSD", "HD", "M.2"]
              },
              {
                "qustion": "המידע נשמר בי באופן מגנטי על ידי צריבה על דיסקים:",
                "bankOptions": ["SSD", "HD", "M.2"]
              },
              {
                "qustion": "אני מתחבר ישירות על חריצים ללוח האם:",
                "bankOptions": ["SSD", "HD", "M.2"]
              }
            ]
          },
          {
            "id": 1,
            "type": "radio",
            "label": "מהו תפקידו של ספק הכוח?",
            "options": [
              "להעביר מידע",
              "לשמור את כל המידע שיש לנו במחשב",
              "להמיר את המתח של רשת החשמל הארצית למתח הנדרש ע\"י המחשב",
              "תשובות א' וב' נכונות"
            ],
            "value": ""
          },
          {
            "id": 1,
            "type": "lineBetween",
            "label": "מתח קו בין רכיב החומרה  לתפקידו:",
            "options": [
              "כרטיס הרחבה",
              "לוח האם",
              "כרטיס RAM",
              "מעבד",
              "ספק כוח"
            ],
            "answers": [
              "כרטיס שנועד להוסיף חיבורים (פורטים) למחשב או להחליף חיבורים תקולים",
              "יחידת העיבוד המרכזית של המחשב, תפקידו לבצע את כל פעולות המחשב",
              "כרטיס לאחסון זיכרון זמני, עליו נשמרים נתונים שרצים בזמן אמת במחשב. * בלעדיו לא יעלה המחשב.",
              "רכיב אליו מחובר כבל המתח, תפקידו להעביר מתח חשמלי לרכיבי המחשב.",
              "לוח אלקטרוני עליו יושבים כל הרכיבים במחשב, אותם הוא מקשר חשמלית."
            ],
            "value": [
              { "opt": "", "ans": "" },
              { "opt": "", "ans": "" },
              { "opt": "", "ans": "" }
            ]
          },
          {
            "id": 1,
            "type": "radio",
            "label": "מה לא נציין לחברה האזרחית כאשר יש לנו תקלה חומרתית במחשב?",
            "options": [
              "תיאור תקלה",
              "לשמור את כל המידע שיש לנו במחשב",
              "תאריך סיום האחריות",
              "המספר הסידורי שעל המדבקה"
            ],
            "value": ""
          },
          {
            "id": 1,
            "type": "radio",
            "label": "באילו סוגי דגמים של מחשבים אנו משתמשים בצ\"הל",
            "options": [
              "נייחים של HP וניידים של dell בלבד",
              "נייחים של DELL וHP וניידים של LENOVO",
              "נייחים של DELL וניידים של HP וLENOVO",
              "נייחים של HP בלבד וניידים של LENOVO ו DEL"
            ],
            "value": ""
          },
          {
            "id": 1,
            "type": "dragDrop",
            "label": "באילו סוגי דגמים של מחשבים אנו משתמשים בצ\"הל",
            "dropColumns": ["בלמ\"ס", "סודי", "סודי ביותר", "סודי שותף"],
            "dragOptions": [
              "כפ\"ג",
              "כפר לוקאלי",
              "עמדה אפורה",
              "צהלנ\"ט",
              "שדה תעופה",
              "Black Edition",
              "משואה",
              "טירת אגם",
              "עין סערה",
              "סיגל"
            ],
            "value": [
              { "opt": "", "ans": "" },
              { "opt": "", "ans": "" },
              { "opt": "", "ans": "" },
              { "opt": "", "ans": "" },
              { "opt": "", "ans": "" },
              { "opt": "", "ans": "" },
              { "opt": "", "ans": "" },
              { "opt": "", "ans": "" },
              { "opt": "", "ans": "" },
              { "opt": "", "ans": "" }
            ]
          }
        ]
      },
      {
        "id": 2,
        "weekId": 1,
        "lessonName": "bbb",
        "pracId": 1,
        "data": [
          {
            "id": 1,
            "type": "radio",
            "label": "סמן את המשפט הנכון ביותר:",
            "options": [
              "ה-SSD הוא אמצעי אחסון בו המידע נשמר דיגיטלית והוא יקר ומהיר יותר מה-HD.",
              "הm.2- הוא אמצעי האחסון הזול ביותר והמידע בו נשמר באמצעות צריבה על דיסקים.",
              "ה-HD שומר מידע באופן דיגיטלי והוא זול יותר מה-M.2."
            ],
            "value": ""
          },
          {
            "id": 1,
            "type": "lineBetween",
            "label": "מתח קו בין רכיב האחסון לרכיבים המחוברים אליו:",
            "options": [
              "ה-SSD הוא אמצעי אחסון בו המידע נשמר דיגיטלית והוא יקר ומהיר יותר מה-HD.",
              "הm.2- הוא אמצעי האחסון הזול ביותר והמידע בו נשמר באמצעות צריבה על דיסקים.",
              "ה-HD שומר מידע באופן דיגיטלי והוא זול יותר מה-M.2."
            ],
            "answers": ["fgfgf", "abbbb", "nnfff"],
            "value": [
              { "opt": "", "ans": "" },
              { "opt": "", "ans": "" },
              { "opt": "", "ans": "" }
            ]
          }
        ]
      }
    ]
  },
  "weeks": {
    "value": [
      {
        "Title": "שבוע 1",
        "id": 1
      },
      {
        "Title": "שבוע 2",
        "id": 2
      },
      {
        "Title": "שבוע 3",
        "id": 3
      },
      {
        "Title": "שבוע 4",
        "id": 4
      },
      {
        "Title": "שבוע 5",
        "id": 5
      }
    ]
  },

  "lessons": {
    "value": [
      {
        "routeName": "aboutThePloga",
        "Title": "שיעור חפיפה 1",
        "description": "הכרת הגדוד",
        "id": 1,
        "weekId": 1,
        "Img": "printer.jpg"
      },
      {
        "routeName": "CMD",
        "Title": "שיעור חפיפה 2",
        "description": "חומרה ומחשבים",
        "id": 2,
        "weekId": 1,
        "Img": "CMD.png"
      },
      {
        "routeName": "pcOperation",
        "Title": "שיעור חפיפה 3",
        "description": "ממשקים במחשב",
        "id": 3,
        "weekId": 1,
        "Img": "pc.jpg",
        "numOfQue": "10"
      },
      {
        "routeName": "hardware&bios",
        "Title": "שיעור חפיפה 4",
        "description": "דומיין ותפעול מחשב",
        "id": 4,
        "weekId": 2,
        "Img": "pc.jpg",
        "numOfQue": "10"
      },
      {
        "routeName": "discs",
        "Title": "שיעור חפיפה 5",
        "description": "תקשורת",
        "id": 5,
        "weekId": 2,
        "Img": "disc.png",
        "numOfQue": "10"
      }
    ]
  }
}
